shamir_mnemonic/__init__.py
shamir_mnemonic/cipher.py
shamir_mnemonic/cli.py
shamir_mnemonic/constants.py
shamir_mnemonic/recovery.py
shamir_mnemonic/rs1024.py
shamir_mnemonic/shamir.py
shamir_mnemonic/share.py
shamir_mnemonic/utils.py
shamir_mnemonic/wordlist.py
shamir_mnemonic/wordlist.txt
shamir_mnemonic_slip39-0.4.3.dist-info/METADATA
shamir_mnemonic_slip39-0.4.3.dist-info/WHEEL
shamir_mnemonic_slip39-0.4.3.dist-info/entry_points.txt
shamir_mnemonic_slip39-0.4.3.dist-info/licenses/LICENSE
shamir_mnemonic_slip39-0.4.3.dist-info/RECORD
