Metadata-Version: 2.4
Name: shamir-mnemonic-slip39
Version: 0.4.3
Summary: SLIP-39 Shamir Mnemonics
License: MIT
License-File: LICENSE
Author: Trezor
Author-email: info@trezor.io
Requires-Python: >=3.6,<4.0
Classifier: License :: OSI Approved :: MIT License
Classifier: Programming Language :: Python :: 3
Classifier: Programming Language :: Python :: 3.6
Classifier: Programming Language :: Python :: 3.7
Classifier: Programming Language :: Python :: 3.8
Classifier: Programming Language :: Python :: 3.9
Classifier: Programming Language :: Python :: 3.10
Classifier: Programming Language :: Python :: 3.11
Classifier: Programming Language :: Python :: 3.12
Classifier: Programming Language :: Python :: 3.13
Classifier: Programming Language :: Python :: 3.14
Provides-Extra: cli
Requires-Dist: click (>=7,<9) ; extra == "cli"
Requires-Dist: dataclasses ; python_full_version <= "3.6.0"
